consul/__init__.py
consul/consul.py
backwork_backup_consul-0.1.0.dist-info/LICENSE
backwork_backup_consul-0.1.0.dist-info/METADATA
backwork_backup_consul-0.1.0.dist-info/WHEEL
backwork_backup_consul-0.1.0.dist-info/entry_points.txt
backwork_backup_consul-0.1.0.dist-info/top_level.txt
backwork_backup_consul-0.1.0.dist-info/RECORD
