Metadata-Version: 2.1
Name: backwork-backup-consul
Version: 0.1.0
Summary: Backwork plug-in for Consul backups.
Home-page: https://github.com/IBM/backwork-backup-consul
Author: Michael Lin
Author-email: michael.lin1@ibm.com
License: Apache 2
Platform: UNKNOWN
Classifier: Development Status :: 3 - Alpha
Classifier: Environment :: Console
Classifier: Intended Audience :: Developers
Classifier: Intended Audience :: System Administrators
Classifier: Operating System :: POSIX :: Linux
Classifier: Programming Language :: Python :: 3 :: Only
Classifier: License :: OSI Approved :: Apache Software License
Classifier: Topic :: Database
Classifier: Topic :: System :: Archiving :: Backup
Classifier: Topic :: Utilities
Requires-Dist: backwork
